deepaffects/__init__.py
deepaffects/api_client.py
deepaffects/configuration.py
deepaffects/rest.py
deepaffects/apis/__init__.py
deepaffects/apis/denoise_api.py
deepaffects/apis/diarize_api.py
deepaffects/apis/diarize_api_v2.py
deepaffects/apis/ellipsis_api.py
deepaffects/apis/emotion_api.py
deepaffects/apis/featurize_api.py
deepaffects/models/__init__.py
deepaffects/models/async_response.py
deepaffects/models/audio.py
deepaffects/models/audio_features.py
deepaffects/models/diarize_audio.py
deepaffects/models/diarize_segment.py
deepaffects/models/emotion_score.py
deepaffects/realtime/__init__.py
deepaffects/realtime/api.py
deepaffects/realtime/deepaffects_realtime_pb2.py
deepaffects/realtime/deepaffects_realtime_pb2_grpc.py
deepaffects/realtime/types.py
deepaffects/realtime/util.py
test/__init__.py
test/test_async_response.py
test/test_audio.py
test/test_base_setup.py
test/test_denoise_api.py
test/test_diarize_api.py
test/test_diarize_api_v2.py
test/test_diarize_audio.py
test/test_emotion_api.py
test/test_emotion_score.py
test/test_featurize_api.py
test/data/clean.wav
test/data/happy.mp3
test/data/noisy.wav
test/data/reconstructed.wav
deepaffects-1.4.1.dist-info/LICENSE
deepaffects-1.4.1.dist-info/METADATA
deepaffects-1.4.1.dist-info/WHEEL
deepaffects-1.4.1.dist-info/top_level.txt
deepaffects-1.4.1.dist-info/RECORD
