Metadata-Version: 2.1
Name: deepaffects
Version: 1.4.1
Summary: Python bindings for DeepAffects APIs
Home-page: https://github.com/SEERNET/deepaffects-python
Author: Sushant Hiray, Venkatesh Duppada
Author-email: support@seernet.io
License: UNKNOWN
Platform: UNKNOWN
Requires-Dist: urllib3 (>=1.15)
Requires-Dist: six (>=1.10)
Requires-Dist: certifi
Requires-Dist: python-dateutil
Requires-Dist: pymediainfo (>=2.1.9)
Requires-Dist: grpcio (==1.13.0)
Requires-Dist: protobuf (==3.6.0)
Requires-Dist: pydub (==0.22.1)
Requires-Dist: pytube (==9.2.2)
